glossary
test_project
