Metadata-Version: 1.1
Name: django-glossary
Version: 0.1.3
Summary: A simple glossary system for Django-powered sites
Home-page: http://github.com/kcunning/django-glossary
Author: Katie Cunningham
Author-email: katie.fulton@gmail.com
License: UNKNOWN
Platform: UNKNOWN
Classifier: Development Status :: 3 - Alpha
Classifier: Programming Language :: Python
Classifier: Environment :: Web Environment
Classifier: Framework :: Django
Classifier: Intended Audience :: Developers
Classifier: License :: OSI Approved :: MIT License
Classifier: Operating System :: OS Independent
Classifier: Programming Language :: Python
Classifier: Topic :: Utilities
Requires: django (>=1.1.1)
